paku_num/__init__.py
paku_num/number.py
paku_num_package_portal-1.0.0.dist-info/LICENSE
paku_num_package_portal-1.0.0.dist-info/METADATA
paku_num_package_portal-1.0.0.dist-info/WHEEL
paku_num_package_portal-1.0.0.dist-info/top_level.txt
paku_num_package_portal-1.0.0.dist-info/RECORD
