Metadata-Version: 2.1
Name: paku-num-package-portal
Version: 1.0.0
Summary: For fun and best !
Home-page: http://robub.rf.gd/
Author: Portal
Author-email: m-9787757@moe-dl.edu.my
License: UNKNOWN
Platform: UNKNOWN
Classifier: Programming Language :: Python :: 3
Classifier: License :: OSI Approved :: MIT License
Classifier: Operating System :: OS Independent
Requires-Python: >=3.6
License-File: LICENSE
